dlacc/__init__.py
dlacc/ansor_engine.py
dlacc/base_class.py
dlacc/main.py
dlacc/metadata.py
dlacc/optimum.py
dlacc/utils.py
dlacc-1.9.dist-info/METADATA
dlacc-1.9.dist-info/WHEEL
dlacc-1.9.dist-info/top_level.txt
dlacc-1.9.dist-info/RECORD
