Metadata-Version: 2.1
Name: dlacc
Version: 1.9
Summary: A simple framework for accelerating deep learning inference runtime.
Home-page: https://github.com/gnomondigital/dlacc.git
Author: gnomondigital
Author-email: contact@gnomondigital.com
License: Apache Software License (http://www.apache.org/licenses/LICENSE-2.0)
Classifier: Development Status :: 4 - Beta
Classifier: Intended Audience :: Developers
Classifier: License :: OSI Approved :: Apache Software License
Classifier: Operating System :: OS Independent
Classifier: Programming Language :: Python :: 3.7
Classifier: Programming Language :: Python :: 3.9
Classifier: Topic :: Internet :: WWW/HTTP :: Dynamic Content
Classifier: Topic :: Internet :: WWW/HTTP :: WSGI :: Application
Classifier: Topic :: Software Development :: Libraries :: Application Frameworks
Classifier: Topic :: Software Development :: Libraries :: Python Modules
Requires-Python: >=3.7
Requires-Dist: onnx
Requires-Dist: onnxruntime
Requires-Dist: pandas
Requires-Dist: google-cloud-storage
Requires-Dist: tvm
